pytest_doctest_mkdocstrings/__init__.py
pytest_doctest_mkdocstrings/doctest_mdcodeblocks.py
test/conftest.py
test/test_plugin.py
test/assets/codeblocks.py
test/assets/test_patch.py
pytest_doctest_mkdocstrings-0.1.1.dist-info/METADATA
pytest_doctest_mkdocstrings-0.1.1.dist-info/WHEEL
pytest_doctest_mkdocstrings-0.1.1.dist-info/entry_points.txt
pytest_doctest_mkdocstrings-0.1.1.dist-info/top_level.txt
pytest_doctest_mkdocstrings-0.1.1.dist-info/RECORD
