Metadata-Version: 2.1
Name: pytest-doctest-mkdocstrings
Version: 0.1.1
Summary: Run pytest --doctest-modules with markdown docstrings in code blocks (```)
Author: Mike Foster
Project-URL: Homepage, https://github.com/MusicalNinjaDad/pytest-doctest-mkdocstrings
Project-URL: Documentation, https://github.com/MusicalNinjaDad/pytest-doctest-mkdocstrings
Project-URL: Repository, https://github.com/MusicalNinjaDad/pytest-doctest-mkdocstrings
Project-URL: Issues, https://github.com/MusicalNinjaDad/pytest-doctest-mkdocstrings/issues
Project-URL: Changelog, https://github.com/MusicalNinjaDad/pytest-doctest-mkdocstrings/blob/main/CHANGELOG.md
Classifier: Programming Language :: Python :: 3
Classifier: License :: OSI Approved :: MIT License
Classifier: Operating System :: OS Independent
Classifier: Framework :: Pytest
Classifier: Intended Audience :: Developers
Classifier: Natural Language :: English
Requires-Python: >=3.7
Requires-Dist: pytest
Provides-Extra: dev
Requires-Dist: mkdocs ; extra == 'dev'
Requires-Dist: mkdocstrings[python] ; extra == 'dev'
Requires-Dist: mkdocs-material ; extra == 'dev'
Requires-Dist: ruff ; extra == 'dev'
